glinkfix/__init__.py
glinkfix/app.py
glinkfix/py.typed
glinkfix/tools.py
glinkfix/version.py
glinkfix/pyproject.toml
glinkfix-2.0.8.dist-info/METADATA
glinkfix-2.0.8.dist-info/WHEEL
glinkfix-2.0.8.dist-info/entry_points.txt
glinkfix-2.0.8.dist-info/licenses/LICENSE
glinkfix-2.0.8.dist-info/licenses/LICENSE-BSD-3-CLAUSE
glinkfix-2.0.8.dist-info/RECORD
