Metadata-Version: 2.4
Name: glinkfix
Version: 2.0.8
Summary: Google Drive Link Fixer
Project-URL: Source Code, https://github.com/geozeke/glinkfix
Project-URL: Bug Tracker, https://github.com/geozeke/glinkfix/issues
Author-email: Peter Nardi <pete@nardi.com>
Maintainer-email: Peter Nardi <pete@nardi.com>
License: MIT License
License-File: LICENSE
License-File: LICENSE-BSD-3-CLAUSE
Keywords: curl,download,drive,embed,glinkfix,google,image,link,markdown
Classifier: Development Status :: 5 - Production/Stable
Classifier: Intended Audience :: Developers
Classifier: License :: OSI Approved :: MIT License
Classifier: Natural Language :: English
Classifier: Operating System :: OS Independent
Classifier: Programming Language :: Python :: 3
Classifier: Programming Language :: Python :: 3.9
Classifier: Programming Language :: Python :: 3.10
Classifier: Programming Language :: Python :: 3.11
Classifier: Programming Language :: Python :: 3.12
Classifier: Programming Language :: Python :: 3.13
Classifier: Topic :: Utilities
Requires-Python: >=3.9
Requires-Dist: pyperclip>=1.9.0
Requires-Dist: tomli>=1.1.0; python_full_version < '3.11'
